audioscrape/__init__.py
audioscrape/__main__.py
audioscrape/classify.py
audioscrape/freesound.py
audioscrape/soundcloud.py
audioscrape/version.py
audioscrape/yamnet.tflite
audioscrape/youtube.py
audioscrape-0.3.1.dist-info/LICENSE
audioscrape-0.3.1.dist-info/METADATA
audioscrape-0.3.1.dist-info/WHEEL
audioscrape-0.3.1.dist-info/entry_points.txt
audioscrape-0.3.1.dist-info/top_level.txt
audioscrape-0.3.1.dist-info/RECORD
