Metadata-Version: 2.1
Name: audioscrape
Version: 0.3.1
Summary: Scrape online audio with a simple command-line interface.
Author-email: Carl Thomé <carlthome@gmail.com>
License: MIT License
Project-URL: Homepage, https://github.com/carlthome/audio-scraper
Project-URL: Bugs, https://github.com/carlthome/audioscrape/issues
Keywords: audio,music,sound
Classifier: Development Status :: 3 - Alpha
Classifier: Intended Audience :: Developers
Classifier: Topic :: Multimedia :: Sound/Audio
Classifier: License :: OSI Approved :: MIT License
Classifier: Programming Language :: Python :: 3
Requires-Python: >=3.8
License-File: LICENSE
Requires-Dist: mediapipe (>=0.10.1)
Requires-Dist: requests (>=2.31.0)
Requires-Dist: soundcloud-lib (>=0.6.1)
Requires-Dist: soundfile (>=0.12.1)
Requires-Dist: tqdm (>=4.65.0)
Requires-Dist: yt-dlp (>=2023.6.22)
Provides-Extra: tests
Requires-Dist: pytest ; extra == 'tests'
Requires-Dist: pytest-cov ; extra == 'tests'
